{"context":{"request_time":"2025-04-06T19:17:47.754735Z","response_time":"2025-04-06T19:17:48.144840Z","response_latency":0.390105,"query":"line=209,direction=inbound"},"success":true,"results":[{"LineId":"209","LineName":"209","Direction":"inbound","IsOutboundOnly":false,"Mode":"bus","LineStrings":["[[[-0.233389,51.485364],[-0.235098,51.483722],[-0.235098,51.483722],[-0.235879,51.482969],[-0.236107,51.482667],[-0.236279,51.482292],[-0.237163,51.480258],[-0.237163,51.480258],[-0.238402,51.477446],[-0.238402,51.477446],[-0.23928,51.47544],[-0.239283,51.475368],[-0.239273,51.475251],[-0.239489,51.475236],[-0.240039,51.475155],[-0.240387,51.47508],[-0.240387,51.47508],[-0.241395,51.474725],[-0.242787,51.474485],[-0.244139,51.474111],[-0.244139,51.474111],[-0.244675,51.474064],[-0.245265,51.474082],[-0.246933,51.473532],[-0.246933,51.473532],[-0.247437,51.473386],[-0.247769,51.473346],[-0.248601,51.473574],[-0.248601,51.473574],[-0.249065,51.473725],[-0.249453,51.473767],[-0.2507,51.473534],[-0.250916,51.473519],[-0.251389,51.473589],[-0.252631,51.472654],[-0.252631,51.472654],[-0.253005,51.472372],[-0.253859,51.471863],[-0.255473,51.471078],[-0.255924,51.470581],[-0.256494,51.470401],[-0.256494,51.470401],[-0.257118,51.470248],[-0.257509,51.470164],[-0.257958,51.470099],[-0.258697,51.469993],[-0.258886,51.469951],[-0.259334,51.469894],[-0.259566,51.469862],[-0.259926,51.46984],[-0.259856,51.469625],[-0.259856,51.469625],[-0.259617,51.468891],[-0.259334,51.467991]]]"],"Stations":[{"RouteId":null,"ParentId":null,"StationId":null,"IcsId":"1001015","TopMostParentId":"490001015BJ","Direction":null,"Towards":"Hammersmith Or Richmond","Modes":["bus"],"StopType":"NaptanPublicBusCoachTram","StopLetter":"BJ","Zone":null,"AccessibilitySummary":null,"HasDisruption":null,"Lines":[{"Id":"209","Name":"209","Uri":"/Line/209","FullName":null,"Type":"Line","Crowding":{"PassengerFlows":[],"TrainLoadings":[]},"RouteType":"Unknown","Status":"Unknown"},{"Id":"378","Name":"378","Uri":"/Line/378","FullName":null,"Type":"Line","Crowding":{"PassengerFlows":[],"TrainLoadings":[]},"RouteType":"Unknown","Status":"Unknown"},{"Id":"419","Name":"419","Uri":"/Line/419","FullName":null,"Type":"Line","Crowding":{"PassengerFlows":[],"TrainLoadings":[]},"RouteType":"Unknown","Status":"Unknown"},{"Id":"533","Name":"533","Uri":"/Line/533","FullName":null,"Type":"Line","Crowding":{"PassengerFlows":[],"TrainLoadings":[]},"RouteType":"Unknown","Status":"Unknown"},{"Id":"969","Name":"969","Uri":"/Line/969","FullName":null,"Type":"Line","Crowding":{"PassengerFlows":[],"TrainLoadings":[]},"RouteType":"Unknown","Status":"Unknown"},{"Id":"n22","Name":"N22","Uri":"/Line/n22","FullName":null,"Type":"Line","Crowding":{"PassengerFlows":[],"TrainLoadings":[]},"RouteType":"Unknown","Status":"Unknown"}],"Status":true,"Id":"490001015BJ","Url":null,"Name":"Barnes Bridge Station","Lat":51.47263,"Lon":-0.25258},{"RouteId":null,"ParentId":null,"StationId":"490G00003628","IcsId":"1003628","TopMostParentId":"490G00003628","Direction":null,"Towards":null,"Modes":["bus"],"StopType":"NaptanOnstreetBusCoachStopPair","StopLetter":null,"Zone":null,"AccessibilitySummary":null,"HasDisruption":null,"Lines":[{"Id":"209","Name":"209","Uri":"/Line/209","FullName":null,"Type":"Line","Crowding":{"PassengerFlows":[],"TrainLoadings":[]},"RouteType":"Unknown","Status":"Unknown"},{"Id":"33","Name":"33","Uri":"/Line/33","FullName":null,"Type":"Line","Crowding":{"PassengerFlows":[],"TrainLoadings":[]},"RouteType":"Unknown","Status":"Unknown"},{"Id":"378","Name":"378","Uri":"/Line/378","FullName":null,"Type":"Line","Crowding":{"PassengerFlows":[],"TrainLoadings":[]},"RouteType":"Unknown","Status":"Unknown"},{"Id":"419","Name":"419","Uri":"/Line/419","FullName":null,"Type":"Line","Crowding":{"PassengerFlows":[],"TrainLoadings":[]},"RouteType":"Unknown","Status":"Unknown"},{"Id":"485","Name":"485","Uri":"/Line/485","FullName":null,"Type":"Line","Crowding":{"PassengerFlows":[],"TrainLoadings":[]},"RouteType":"Unknown","Status":"Unknown"},{"Id":"533","Name":"533","Uri":"/Line/533","FullName":null,"Type":"Line","Crowding":{"PassengerFlows":[],"TrainLoadings":[]},"RouteType":"Unknown","Status":"Unknown"},{"Id":"969","Name":"969","Uri":"/Line/969","FullName":null,"Type":"Line","Crowding":{"PassengerFlows":[],"TrainLoadings":[]},"RouteType":"Unknown","Status":"Unknown"},{"Id":"n22","Name":"N22","Uri":"/Line/n22","FullName":null,"Type":"Line","Crowding":{"PassengerFlows":[],"TrainLoadings":[]},"RouteType":"Unknown","Status":"Unknown"}],"Status":true,"Id":"490G00003628","Url":null,"Name":"Barnes / Red Lion","Lat":51.47504,"Lon":-0.24036},{"RouteId":null,"ParentId":null,"StationId":"490G00003630","IcsId":"1003630","TopMostParentId":"490G00003630","Direction":null,"Towards":null,"Modes":["bus"],"StopType":"NaptanOnstreetBusCoachStopPair","StopLetter":null,"Zone":null,"AccessibilitySummary":null,"HasDisruption":null,"Lines":[{"Id":"209","Name":"209","Uri":"/Line/209","FullName":null,"Type":"Line","Crowding":{"PassengerFlows":[],"TrainLoadings":[]},"RouteType":"Unknown","Status":"Unknown"},{"Id":"378","Name":"378","Uri":"/Line/378","FullName":null,"Type":"Line","Crowding":{"PassengerFlows":[],"TrainLoadings":[]},"RouteType":"Unknown","Status":"Unknown"},{"Id":"533","Name":"533","Uri":"/Line/533","FullName":null,"Type":"Line","Crowding":{"PassengerFlows":[],"TrainLoadings":[]},"RouteType":"Unknown","Status":"Unknown"},{"Id":"969","Name":"969","Uri":"/Line/969","FullName":null,"Type":"Line","Crowding":{"PassengerFlows":[],"TrainLoadings":[]},"RouteType":"Unknown","Status":"Unknown"},{"Id":"n22","Name":"N22","Uri":"/Line/n22","FullName":null,"Type":"Line","Crowding":{"PassengerFlows":[],"TrainLoadings":[]},"RouteType":"Unknown","Status":"Unknown"}],"Status":true,"Id":"490G00003630","Url":null,"Name":"Barnes High Street","Lat":51.47351,"Lon":-0.25057},{"RouteId":null,"ParentId":null,"StationId":"490G00003632","IcsId":"1003632","TopMostParentId":"490G00003632","Direction":null,"Towards":null,"Modes":["bus"],"StopType":"NaptanOnstreetBusCoachStopPair","StopLetter":null,"Zone":null,"AccessibilitySummary":null,"HasDisruption":null,"Lines":[{"Id":"209","Name":"209","Uri":"/Line/209","FullName":null,"Type":"Line","Crowding":{"PassengerFlows":[],"TrainLoadings":[]},"RouteType":"Unknown","Status":"Unknown"},{"Id":"378","Name":"378","Uri":"/Line/378","FullName":null,"Type":"Line","Crowding":{"PassengerFlows":[],"TrainLoadings":[]},"RouteType":"Unknown","Status":"Unknown"},{"Id":"485","Name":"485","Uri":"/Line/485","FullName":null,"Type":"Line","Crowding":{"PassengerFlows":[],"TrainLoadings":[]},"RouteType":"Unknown","Status":"Unknown"},{"Id":"533","Name":"533","Uri":"/Line/533","FullName":null,"Type":"Line","Crowding":{"PassengerFlows":[],"TrainLoadings":[]},"RouteType":"Unknown","Status":"Unknown"},{"Id":"969","Name":"969","Uri":"/Line/969","FullName":null,"Type":"Line","Crowding":{"PassengerFlows":[],"TrainLoadings":[]},"RouteType":"Unknown","Status":"Unknown"},{"Id":"n22","Name":"N22","Uri":"/Line/n22","FullName":null,"Type":"Line","Crowding":{"PassengerFlows":[],"TrainLoadings":[]},"RouteType":"Unknown","Status":"Unknown"}],"Status":true,"Id":"490G00003632","Url":null,"Name":"Barnes Pond","Lat":51.47339,"Lon":-0.24682},{"RouteId":null,"ParentId":null,"StationId":"490G00007216","IcsId":"1007216","TopMostParentId":"490G00007216","Direction":null,"Towards":null,"Modes":["bus"],"StopType":"NaptanOnstreetBusCoachStopPair","StopLetter":null,"Zone":null,"AccessibilitySummary":null,"HasDisruption":null,"Lines":[{"Id":"209","Name":"209","Uri":"/Line/209","FullName":null,"Type":"Line","Crowding":{"PassengerFlows":[],"TrainLoadings":[]},"RouteType":"Unknown","Status":"Unknown"},{"Id":"378","Name":"378","Uri":"/Line/378","FullName":null,"Type":"Line","Crowding":{"PassengerFlows":[],"TrainLoadings":[]},"RouteType":"Unknown","Status":"Unknown"},{"Id":"485","Name":"485","Uri":"/Line/485","FullName":null,"Type":"Line","Crowding":{"PassengerFlows":[],"TrainLoadings":[]},"RouteType":"Unknown","Status":"Unknown"},{"Id":"533","Name":"533","Uri":"/Line/533","FullName":null,"Type":"Line","Crowding":{"PassengerFlows":[],"TrainLoadings":[]},"RouteType":"Unknown","Status":"Unknown"},{"Id":"969","Name":"969","Uri":"/Line/969","FullName":null,"Type":"Line","Crowding":{"PassengerFlows":[],"TrainLoadings":[]},"RouteType":"Unknown","Status":"Unknown"},{"Id":"n22","Name":"N22","Uri":"/Line/n22","FullName":null,"Type":"Line","Crowding":{"PassengerFlows":[],"TrainLoadings":[]},"RouteType":"Unknown","Status":"Unknown"}],"Status":true,"Id":"490G00007216","Url":null,"Name":"Glebe Road","Lat":51.47443,"Lon":-0.24371},{"RouteId":null,"ParentId":null,"StationId":"490G00009353","IcsId":"1009353","TopMostParentId":"490G00009353","Direction":null,"Towards":null,"Modes":["bus"],"StopType":"NaptanOnstreetBusCoachStopPair","StopLetter":null,"Zone":null,"AccessibilitySummary":null,"HasDisruption":null,"Lines":[{"Id":"209","Name":"209","Uri":"/Line/209","FullName":null,"Type":"Line","Crowding":{"PassengerFlows":[],"TrainLoadings":[]},"RouteType":"Unknown","Status":"Unknown"},{"Id":"33","Name":"33","Uri":"/Line/33","FullName":null,"Type":"Line","Crowding":{"PassengerFlows":[],"TrainLoadings":[]},"RouteType":"Unknown","Status":"Unknown"},{"Id":"419","Name":"419","Uri":"/Line/419","FullName":null,"Type":"Line","Crowding":{"PassengerFlows":[],"TrainLoadings":[]},"RouteType":"Unknown","Status":"Unknown"},{"Id":"485","Name":"485","Uri":"/Line/485","FullName":null,"Type":"Line","Crowding":{"PassengerFlows":[],"TrainLoadings":[]},"RouteType":"Unknown","Status":"Unknown"},{"Id":"533","Name":"533","Uri":"/Line/533","FullName":null,"Type":"Line","Crowding":{"PassengerFlows":[],"TrainLoadings":[]},"RouteType":"Unknown","Status":"Unknown"}],"Status":true,"Id":"490G00009353","Url":null,"Name":"Lonsdale Road","Lat":51.48519,"Lon":-0.23358},{"RouteId":null,"ParentId":null,"StationId":"490G00010047","IcsId":"1010047","TopMostParentId":"490G00010047","Direction":null,"Towards":null,"Modes":["bus"],"StopType":"NaptanOnstreetBusCoachStopPair","StopLetter":null,"Zone":null,"AccessibilitySummary":null,"HasDisruption":null,"Lines":[{"Id":"209","Name":"209","Uri":"/Line/209","FullName":null,"Type":"Line","Crowding":{"PassengerFlows":[],"TrainLoadings":[]},"RouteType":"Unknown","Status":"Unknown"},{"Id":"378","Name":"378","Uri":"/Line/378","FullName":null,"Type":"Line","Crowding":{"PassengerFlows":[],"TrainLoadings":[]},"RouteType":"Unknown","Status":"Unknown"}],"Status":true,"Id":"490G00010047","Url":null,"Name":"Mortlake Bus Station","Lat":51.46801,"Lon":-0.25958},{"RouteId":null,"ParentId":null,"StationId":"490G00010246","IcsId":"1010246","TopMostParentId":"490G00010246","Direction":null,"Towards":null,"Modes":["bus"],"StopType":"NaptanOnstreetBusCoachStopPair","StopLetter":null,"Zone":null,"AccessibilitySummary":null,"HasDisruption":null,"Lines":[{"Id":"209","Name":"209","Uri":"/Line/209","FullName":null,"Type":"Line","Crowding":{"PassengerFlows":[],"TrainLoadings":[]},"RouteType":"Unknown","Status":"Unknown"},{"Id":"33","Name":"33","Uri":"/Line/33","FullName":null,"Type":"Line","Crowding":{"PassengerFlows":[],"TrainLoadings":[]},"RouteType":"Unknown","Status":"Unknown"},{"Id":"419","Name":"419","Uri":"/Line/419","FullName":null,"Type":"Line","Crowding":{"PassengerFlows":[],"TrainLoadings":[]},"RouteType":"Unknown","Status":"Unknown"},{"Id":"485","Name":"485","Uri":"/Line/485","FullName":null,"Type":"Line","Crowding":{"PassengerFlows":[],"TrainLoadings":[]},"RouteType":"Unknown","Status":"Unknown"},{"Id":"533","Name":"533","Uri":"/Line/533","FullName":null,"Type":"Line","Crowding":{"PassengerFlows":[],"TrainLoadings":[]},"RouteType":"Unknown","Status":"Unknown"}],"Status":true,"Id":"490G00010246","Url":null,"Name":"Newport Road","Lat":51.47743,"Lon":-0.23831},{"RouteId":null,"ParentId":null,"StationId":"490G00013558","IcsId":"1013558","TopMostParentId":"490G00013558","Direction":null,"Towards":null,"Modes":["bus"],"StopType":"NaptanOnstreetBusCoachStopPair","StopLetter":null,"Zone":null,"AccessibilitySummary":null,"HasDisruption":null,"Lines":[{"Id":"209","Name":"209","Uri":"/Line/209","FullName":null,"Type":"Line","Crowding":{"PassengerFlows":[],"TrainLoadings":[]},"RouteType":"Unknown","Status":"Unknown"},{"Id":"33","Name":"33","Uri":"/Line/33","FullName":null,"Type":"Line","Crowding":{"PassengerFlows":[],"TrainLoadings":[]},"RouteType":"Unknown","Status":"Unknown"},{"Id":"419","Name":"419","Uri":"/Line/419","FullName":null,"Type":"Line","Crowding":{"PassengerFlows":[],"TrainLoadings":[]},"RouteType":"Unknown","Status":"Unknown"},{"Id":"485","Name":"485","Uri":"/Line/485","FullName":null,"Type":"Line","Crowding":{"PassengerFlows":[],"TrainLoadings":[]},"RouteType":"Unknown","Status":"Unknown"},{"Id":"533","Name":"533","Uri":"/Line/533","FullName":null,"Type":"Line","Crowding":{"PassengerFlows":[],"TrainLoadings":[]},"RouteType":"Unknown","Status":"Unknown"}],"Status":true,"Id":"490G00013558","Url":null,"Name":"The Spinney","Lat":51.48361,"Lon":-0.23534},{"RouteId":null,"ParentId":null,"StationId":"490G00014260","IcsId":"1014260","TopMostParentId":"490G00014260","Direction":null,"Towards":null,"Modes":["bus"],"StopType":"NaptanOnstreetBusCoachStopPair","StopLetter":null,"Zone":null,"AccessibilitySummary":null,"HasDisruption":null,"Lines":[{"Id":"209","Name":"209","Uri":"/Line/209","FullName":null,"Type":"Line","Crowding":{"PassengerFlows":[],"TrainLoadings":[]},"RouteType":"Unknown","Status":"Unknown"},{"Id":"33","Name":"33","Uri":"/Line/33","FullName":null,"Type":"Line","Crowding":{"PassengerFlows":[],"TrainLoadings":[]},"RouteType":"Unknown","Status":"Unknown"},{"Id":"419","Name":"419","Uri":"/Line/419","FullName":null,"Type":"Line","Crowding":{"PassengerFlows":[],"TrainLoadings":[]},"RouteType":"Unknown","Status":"Unknown"},{"Id":"485","Name":"485","Uri":"/Line/485","FullName":null,"Type":"Line","Crowding":{"PassengerFlows":[],"TrainLoadings":[]},"RouteType":"Unknown","Status":"Unknown"},{"Id":"533","Name":"533","Uri":"/Line/533","FullName":null,"Type":"Line","Crowding":{"PassengerFlows":[],"TrainLoadings":[]},"RouteType":"Unknown","Status":"Unknown"}],"Status":true,"Id":"490G00014260","Url":null,"Name":"Washington Road","Lat":51.48024,"Lon":-0.23708},{"RouteId":null,"ParentId":null,"StationId":"490G00014596","IcsId":"1014596","TopMostParentId":"490G00014596","Direction":null,"Towards":null,"Modes":["bus"],"StopType":"NaptanOnstreetBusCoachStopPair","StopLetter":null,"Zone":null,"AccessibilitySummary":null,"HasDisruption":null,"Lines":[{"Id":"209","Name":"209","Uri":"/Line/209","FullName":null,"Type":"Line","Crowding":{"PassengerFlows":[],"TrainLoadings":[]},"RouteType":"Unknown","Status":"Unknown"},{"Id":"378","Name":"378","Uri":"/Line/378","FullName":null,"Type":"Line","Crowding":{"PassengerFlows":[],"TrainLoadings":[]},"RouteType":"Unknown","Status":"Unknown"},{"Id":"419","Name":"419","Uri":"/Line/419","FullName":null,"Type":"Line","Crowding":{"PassengerFlows":[],"TrainLoadings":[]},"RouteType":"Unknown","Status":"Unknown"},{"Id":"533","Name":"533","Uri":"/Line/533","FullName":null,"Type":"Line","Crowding":{"PassengerFlows":[],"TrainLoadings":[]},"RouteType":"Unknown","Status":"Unknown"},{"Id":"969","Name":"969","Uri":"/Line/969","FullName":null,"Type":"Line","Crowding":{"PassengerFlows":[],"TrainLoadings":[]},"RouteType":"Unknown","Status":"Unknown"},{"Id":"n22","Name":"N22","Uri":"/Line/n22","FullName":null,"Type":"Line","Crowding":{"PassengerFlows":[],"TrainLoadings":[]},"RouteType":"Unknown","Status":"Unknown"}],"Status":true,"Id":"490G00014596","Url":null,"Name":"White Hart Lane","Lat":51.47024,"Lon":-0.25676},{"RouteId":null,"ParentId":null,"StationId":"490G000373","IcsId":"1002152","TopMostParentId":"490G000373","Direction":null,"Towards":null,"Modes":["bus"],"StopType":"NaptanOnstreetBusCoachStopPair","StopLetter":null,"Zone":null,"AccessibilitySummary":null,"HasDisruption":null,"Lines":[{"Id":"209","Name":"209","Uri":"/Line/209","FullName":null,"Type":"Line","Crowding":{"PassengerFlows":[],"TrainLoadings":[]},"RouteType":"Unknown","Status":"Unknown"},{"Id":"378","Name":"378","Uri":"/Line/378","FullName":null,"Type":"Line","Crowding":{"PassengerFlows":[],"TrainLoadings":[]},"RouteType":"Unknown","Status":"Unknown"},{"Id":"419","Name":"419","Uri":"/Line/419","FullName":null,"Type":"Line","Crowding":{"PassengerFlows":[],"TrainLoadings":[]},"RouteType":"Unknown","Status":"Unknown"},{"Id":"533","Name":"533","Uri":"/Line/533","FullName":null,"Type":"Line","Crowding":{"PassengerFlows":[],"TrainLoadings":[]},"RouteType":"Unknown","Status":"Unknown"},{"Id":"969","Name":"969","Uri":"/Line/969","FullName":null,"Type":"Line","Crowding":{"PassengerFlows":[],"TrainLoadings":[]},"RouteType":"Unknown","Status":"Unknown"},{"Id":"n22","Name":"N22","Uri":"/Line/n22","FullName":null,"Type":"Line","Crowding":{"PassengerFlows":[],"TrainLoadings":[]},"RouteType":"Unknown","Status":"Unknown"}],"Status":true,"Id":"490G000373","Url":null,"Name":"Avondale Road","Lat":51.46963,"Lon":-0.2598}],"StopPointSequences":[{"LineId":"209","LineName":"209","Direction":"inbound","BranchId":0,"NextBranchIds":[],"PrevBranchIds":[],"StopPoint":[{"RouteId":null,"ParentId":"490G00009353","StationId":"490G00009353","IcsId":"1009353","TopMostParentId":"490G00009353","Direction":null,"Towards":"Mortlake, Putney Or Sheen","Modes":["bus"],"StopType":"NaptanPublicBusCoachTram","StopLetter":"K","Zone":null,"AccessibilitySummary":null,"HasDisruption":null,"Lines":[{"Id":"209","Name":"209","Uri":"/Line/209","FullName":null,"Type":"Line","Crowding":{"PassengerFlows":[],"TrainLoadings":[]},"RouteType":"Unknown","Status":"Unknown"},{"Id":"33","Name":"33","Uri":"/Line/33","FullName":null,"Type":"Line","Crowding":{"PassengerFlows":[],"TrainLoadings":[]},"RouteType":"Unknown","Status":"Unknown"},{"Id":"419","Name":"419","Uri":"/Line/419","FullName":null,"Type":"Line","Crowding":{"PassengerFlows":[],"TrainLoadings":[]},"RouteType":"Unknown","Status":"Unknown"},{"Id":"485","Name":"485","Uri":"/Line/485","FullName":null,"Type":"Line","Crowding":{"PassengerFlows":[],"TrainLoadings":[]},"RouteType":"Unknown","Status":"Unknown"},{"Id":"533","Name":"533","Uri":"/Line/533","FullName":null,"Type":"Line","Crowding":{"PassengerFlows":[],"TrainLoadings":[]},"RouteType":"Unknown","Status":"Unknown"}],"Status":true,"Id":"490009353S","Url":null,"Name":"Lonsdale Road","Lat":51.48535,"Lon":-0.23335},{"RouteId":null,"ParentId":"490G00013558","StationId":"490G00013558","IcsId":"1013558","TopMostParentId":"490G00013558","Direction":null,"Towards":"Mortlake, Putney Or Sheen","Modes":["bus"],"StopType":"NaptanPublicBusCoachTram","StopLetter":"L","Zone":null,"AccessibilitySummary":null,"HasDisruption":null,"Lines":[{"Id":"209","Name":"209","Uri":"/Line/209","FullName":null,"Type":"Line","Crowding":{"PassengerFlows":[],"TrainLoadings":[]},"RouteType":"Unknown","Status":"Unknown"},{"Id":"33","Name":"33","Uri":"/Line/33","FullName":null,"Type":"Line","Crowding":{"PassengerFlows":[],"TrainLoadings":[]},"RouteType":"Unknown","Status":"Unknown"},{"Id":"419","Name":"419","Uri":"/Line/419","FullName":null,"Type":"Line","Crowding":{"PassengerFlows":[],"TrainLoadings":[]},"RouteType":"Unknown","Status":"Unknown"},{"Id":"485","Name":"485","Uri":"/Line/485","FullName":null,"Type":"Line","Crowding":{"PassengerFlows":[],"TrainLoadings":[]},"RouteType":"Unknown","Status":"Unknown"},{"Id":"533","Name":"533","Uri":"/Line/533","FullName":null,"Type":"Line","Crowding":{"PassengerFlows":[],"TrainLoadings":[]},"RouteType":"Unknown","Status":"Unknown"}],"Status":true,"Id":"490013558S","Url":null,"Name":"The Spinney","Lat":51.4834,"Lon":-0.23524},{"RouteId":null,"ParentId":"490G00014260","StationId":"490G00014260","IcsId":"1014260","TopMostParentId":"490G00014260","Direction":null,"Towards":"Mortlake, Putney Or Sheen","Modes":["bus"],"StopType":"NaptanPublicBusCoachTram","StopLetter":"M","Zone":null,"AccessibilitySummary":null,"HasDisruption":null,"Lines":[{"Id":"209","Name":"209","Uri":"/Line/209","FullName":null,"Type":"Line","Crowding":{"PassengerFlows":[],"TrainLoadings":[]},"RouteType":"Unknown","Status":"Unknown"},{"Id":"33","Name":"33","Uri":"/Line/33","FullName":null,"Type":"Line","Crowding":{"PassengerFlows":[],"TrainLoadings":[]},"RouteType":"Unknown","Status":"Unknown"},{"Id":"419","Name":"419","Uri":"/Line/419","FullName":null,"Type":"Line","Crowding":{"PassengerFlows":[],"TrainLoadings":[]},"RouteType":"Unknown","Status":"Unknown"},{"Id":"485","Name":"485","Uri":"/Line/485","FullName":null,"Type":"Line","Crowding":{"PassengerFlows":[],"TrainLoadings":[]},"RouteType":"Unknown","Status":"Unknown"},{"Id":"533","Name":"533","Uri":"/Line/533","FullName":null,"Type":"Line","Crowding":{"PassengerFlows":[],"TrainLoadings":[]},"RouteType":"Unknown","Status":"Unknown"}],"Status":true,"Id":"490014260S","Url":null,"Name":"Washington Road","Lat":51.48024,"Lon":-0.23708},{"RouteId":null,"ParentId":"490G00010246","StationId":"490G00010246","IcsId":"1010246","TopMostParentId":"490G00010246","Direction":null,"Towards":"Mortlake, Putney Or Sheen","Modes":["bus"],"StopType":"NaptanPublicBusCoachTram","StopLetter":"WN","Zone":null,"AccessibilitySummary":null,"HasDisruption":null,"Lines":[{"Id":"209","Name":"209","Uri":"/Line/209","FullName":null,"Type":"Line","Crowding":{"PassengerFlows":[],"TrainLoadings":[]},"RouteType":"Unknown","Status":"Unknown"},{"Id":"33","Name":"33","Uri":"/Line/33","FullName":null,"Type":"Line","Crowding":{"PassengerFlows":[],"TrainLoadings":[]},"RouteType":"Unknown","Status":"Unknown"},{"Id":"419","Name":"419","Uri":"/Line/419","FullName":null,"Type":"Line","Crowding":{"PassengerFlows":[],"TrainLoadings":[]},"RouteType":"Unknown","Status":"Unknown"},{"Id":"485","Name":"485","Uri":"/Line/485","FullName":null,"Type":"Line","Crowding":{"PassengerFlows":[],"TrainLoadings":[]},"RouteType":"Unknown","Status":"Unknown"},{"Id":"533","Name":"533","Uri":"/Line/533","FullName":null,"Type":"Line","Crowding":{"PassengerFlows":[],"TrainLoadings":[]},"RouteType":"Unknown","Status":"Unknown"}],"Status":true,"Id":"490010246WN","Url":null,"Name":"Newport Road","Lat":51.47743,"Lon":-0.23831},{"RouteId":null,"ParentId":"490G00003628","StationId":"490G00003628","IcsId":"1003628","TopMostParentId":"490G00003628","Direction":null,"Towards":"Mortlake Or Putney","Modes":["bus"],"StopType":"NaptanPublicBusCoachTram","StopLetter":"BA","Zone":null,"AccessibilitySummary":null,"HasDisruption":null,"Lines":[{"Id":"209","Name":"209","Uri":"/Line/209","FullName":null,"Type":"Line","Crowding":{"PassengerFlows":[],"TrainLoadings":[]},"RouteType":"Unknown","Status":"Unknown"},{"Id":"378","Name":"378","Uri":"/Line/378","FullName":null,"Type":"Line","Crowding":{"PassengerFlows":[],"TrainLoadings":[]},"RouteType":"Unknown","Status":"Unknown"},{"Id":"485","Name":"485","Uri":"/Line/485","FullName":null,"Type":"Line","Crowding":{"PassengerFlows":[],"TrainLoadings":[]},"RouteType":"Unknown","Status":"Unknown"},{"Id":"533","Name":"533","Uri":"/Line/533","FullName":null,"Type":"Line","Crowding":{"PassengerFlows":[],"TrainLoadings":[]},"RouteType":"Unknown","Status":"Unknown"},{"Id":"969","Name":"969","Uri":"/Line/969","FullName":null,"Type":"Line","Crowding":{"PassengerFlows":[],"TrainLoadings":[]},"RouteType":"Unknown","Status":"Unknown"},{"Id":"n22","Name":"N22","Uri":"/Line/n22","FullName":null,"Type":"Line","Crowding":{"PassengerFlows":[],"TrainLoadings":[]},"RouteType":"Unknown","Status":"Unknown"}],"Status":true,"Id":"490003628BA","Url":null,"Name":"Barnes / Red Lion","Lat":51.47504,"Lon":-0.24036},{"RouteId":null,"ParentId":"490G00007216","StationId":"490G00007216","IcsId":"1007216","TopMostParentId":"490G00007216","Direction":null,"Towards":"Mortlake Or Putney","Modes":["bus"],"StopType":"NaptanPublicBusCoachTram","StopLetter":"BB","Zone":null,"AccessibilitySummary":null,"HasDisruption":null,"Lines":[{"Id":"209","Name":"209","Uri":"/Line/209","FullName":null,"Type":"Line","Crowding":{"PassengerFlows":[],"TrainLoadings":[]},"RouteType":"Unknown","Status":"Unknown"},{"Id":"378","Name":"378","Uri":"/Line/378","FullName":null,"Type":"Line","Crowding":{"PassengerFlows":[],"TrainLoadings":[]},"RouteType":"Unknown","Status":"Unknown"},{"Id":"485","Name":"485","Uri":"/Line/485","FullName":null,"Type":"Line","Crowding":{"PassengerFlows":[],"TrainLoadings":[]},"RouteType":"Unknown","Status":"Unknown"},{"Id":"533","Name":"533","Uri":"/Line/533","FullName":null,"Type":"Line","Crowding":{"PassengerFlows":[],"TrainLoadings":[]},"RouteType":"Unknown","Status":"Unknown"},{"Id":"969","Name":"969","Uri":"/Line/969","FullName":null,"Type":"Line","Crowding":{"PassengerFlows":[],"TrainLoadings":[]},"RouteType":"Unknown","Status":"Unknown"},{"Id":"n22","Name":"N22","Uri":"/Line/n22","FullName":null,"Type":"Line","Crowding":{"PassengerFlows":[],"TrainLoadings":[]},"RouteType":"Unknown","Status":"Unknown"}],"Status":true,"Id":"490007216BB","Url":null,"Name":"Glebe Road","Lat":51.47396,"Lon":-0.24459},{"RouteId":null,"ParentId":"490G00003632","StationId":"490G00003632","IcsId":"1003632","TopMostParentId":"490G00003632","Direction":null,"Towards":"Mortlake Or Putney","Modes":["bus"],"StopType":"NaptanPublicBusCoachTram","StopLetter":"BD","Zone":null,"AccessibilitySummary":null,"HasDisruption":null,"Lines":[{"Id":"209","Name":"209","Uri":"/Line/209","FullName":null,"Type":"Line","Crowding":{"PassengerFlows":[],"TrainLoadings":[]},"RouteType":"Unknown","Status":"Unknown"},{"Id":"378","Name":"378","Uri":"/Line/378","FullName":null,"Type":"Line","Crowding":{"PassengerFlows":[],"TrainLoadings":[]},"RouteType":"Unknown","Status":"Unknown"},{"Id":"485","Name":"485","Uri":"/Line/485","FullName":null,"Type":"Line","Crowding":{"PassengerFlows":[],"TrainLoadings":[]},"RouteType":"Unknown","Status":"Unknown"},{"Id":"533","Name":"533","Uri":"/Line/533","FullName":null,"Type":"Line","Crowding":{"PassengerFlows":[],"TrainLoadings":[]},"RouteType":"Unknown","Status":"Unknown"},{"Id":"969","Name":"969","Uri":"/Line/969","FullName":null,"Type":"Line","Crowding":{"PassengerFlows":[],"TrainLoadings":[]},"RouteType":"Unknown","Status":"Unknown"},{"Id":"n22","Name":"N22","Uri":"/Line/n22","FullName":null,"Type":"Line","Crowding":{"PassengerFlows":[],"TrainLoadings":[]},"RouteType":"Unknown","Status":"Unknown"}],"Status":true,"Id":"490003632BD","Url":null,"Name":"Barnes Pond","Lat":51.47339,"Lon":-0.24682},{"RouteId":null,"ParentId":"490G00003630","StationId":"490G00003630","IcsId":"1003630","TopMostParentId":"490G00003630","Direction":null,"Towards":"Mortlake","Modes":["bus"],"StopType":"NaptanPublicBusCoachTram","StopLetter":"BH","Zone":null,"AccessibilitySummary":null,"HasDisruption":null,"Lines":[{"Id":"209","Name":"209","Uri":"/Line/209","FullName":null,"Type":"Line","Crowding":{"PassengerFlows":[],"TrainLoadings":[]},"RouteType":"Unknown","Status":"Unknown"},{"Id":"378","Name":"378","Uri":"/Line/378","FullName":null,"Type":"Line","Crowding":{"PassengerFlows":[],"TrainLoadings":[]},"RouteType":"Unknown","Status":"Unknown"},{"Id":"533","Name":"533","Uri":"/Line/533","FullName":null,"Type":"Line","Crowding":{"PassengerFlows":[],"TrainLoadings":[]},"RouteType":"Unknown","Status":"Unknown"},{"Id":"969","Name":"969","Uri":"/Line/969","FullName":null,"Type":"Line","Crowding":{"PassengerFlows":[],"TrainLoadings":[]},"RouteType":"Unknown","Status":"Unknown"},{"Id":"n22","Name":"N22","Uri":"/Line/n22","FullName":null,"Type":"Line","Crowding":{"PassengerFlows":[],"TrainLoadings":[]},"RouteType":"Unknown","Status":"Unknown"}],"Status":true,"Id":"490003630BH","Url":null,"Name":"Barnes High Street","Lat":51.47356,"Lon":-0.24874},{"RouteId":null,"ParentId":null,"StationId":null,"IcsId":"1001015","TopMostParentId":"490001015BJ","Direction":null,"Towards":"Hammersmith Or Richmond","Modes":["bus"],"StopType":"NaptanPublicBusCoachTram","StopLetter":"BJ","Zone":null,"AccessibilitySummary":null,"HasDisruption":null,"Lines":[{"Id":"209","Name":"209","Uri":"/Line/209","FullName":null,"Type":"Line","Crowding":{"PassengerFlows":[],"TrainLoadings":[]},"RouteType":"Unknown","Status":"Unknown"},{"Id":"378","Name":"378","Uri":"/Line/378","FullName":null,"Type":"Line","Crowding":{"PassengerFlows":[],"TrainLoadings":[]},"RouteType":"Unknown","Status":"Unknown"},{"Id":"419","Name":"419","Uri":"/Line/419","FullName":null,"Type":"Line","Crowding":{"PassengerFlows":[],"TrainLoadings":[]},"RouteType":"Unknown","Status":"Unknown"},{"Id":"533","Name":"533","Uri":"/Line/533","FullName":null,"Type":"Line","Crowding":{"PassengerFlows":[],"TrainLoadings":[]},"RouteType":"Unknown","Status":"Unknown"},{"Id":"969","Name":"969","Uri":"/Line/969","FullName":null,"Type":"Line","Crowding":{"PassengerFlows":[],"TrainLoadings":[]},"RouteType":"Unknown","Status":"Unknown"},{"Id":"n22","Name":"N22","Uri":"/Line/n22","FullName":null,"Type":"Line","Crowding":{"PassengerFlows":[],"TrainLoadings":[]},"RouteType":"Unknown","Status":"Unknown"}],"Status":true,"Id":"490001015BJ","Url":null,"Name":"Barnes Bridge Station","Lat":51.47263,"Lon":-0.25258},{"RouteId":null,"ParentId":"490G00014596","StationId":"490G00014596","IcsId":"1014596","TopMostParentId":"490G00014596","Direction":null,"Towards":"Hammersmith Or Richmond","Modes":["bus"],"StopType":"NaptanPublicBusCoachTram","StopLetter":"V","Zone":null,"AccessibilitySummary":null,"HasDisruption":null,"Lines":[{"Id":"209","Name":"209","Uri":"/Line/209","FullName":null,"Type":"Line","Crowding":{"PassengerFlows":[],"TrainLoadings":[]},"RouteType":"Unknown","Status":"Unknown"},{"Id":"378","Name":"378","Uri":"/Line/378","FullName":null,"Type":"Line","Crowding":{"PassengerFlows":[],"TrainLoadings":[]},"RouteType":"Unknown","Status":"Unknown"},{"Id":"419","Name":"419","Uri":"/Line/419","FullName":null,"Type":"Line","Crowding":{"PassengerFlows":[],"TrainLoadings":[]},"RouteType":"Unknown","Status":"Unknown"},{"Id":"533","Name":"533","Uri":"/Line/533","FullName":null,"Type":"Line","Crowding":{"PassengerFlows":[],"TrainLoadings":[]},"RouteType":"Unknown","Status":"Unknown"},{"Id":"969","Name":"969","Uri":"/Line/969","FullName":null,"Type":"Line","Crowding":{"PassengerFlows":[],"TrainLoadings":[]},"RouteType":"Unknown","Status":"Unknown"},{"Id":"n22","Name":"N22","Uri":"/Line/n22","FullName":null,"Type":"Line","Crowding":{"PassengerFlows":[],"TrainLoadings":[]},"RouteType":"Unknown","Status":"Unknown"}],"Status":true,"Id":"490014596W","Url":null,"Name":"White Hart Lane","Lat":51.47024,"Lon":-0.25676},{"RouteId":null,"ParentId":"490G000373","StationId":"490G000373","IcsId":"1002152","TopMostParentId":"490G000373","Direction":null,"Towards":"Mortlake Bus Station","Modes":["bus"],"StopType":"NaptanPublicBusCoachTram","StopLetter":"X","Zone":null,"AccessibilitySummary":null,"HasDisruption":null,"Lines":[{"Id":"209","Name":"209","Uri":"/Line/209","FullName":null,"Type":"Line","Crowding":{"PassengerFlows":[],"TrainLoadings":[]},"RouteType":"Unknown","Status":"Unknown"},{"Id":"378","Name":"378","Uri":"/Line/378","FullName":null,"Type":"Line","Crowding":{"PassengerFlows":[],"TrainLoadings":[]},"RouteType":"Unknown","Status":"Unknown"}],"Status":true,"Id":"490006144S","Url":null,"Name":"Avondale Road","Lat":51.46963,"Lon":-0.2598},{"RouteId":null,"ParentId":"490G00010047","StationId":"490G00010047","IcsId":"1010047","TopMostParentId":"490G00010047","Direction":null,"Towards":null,"Modes":["bus"],"StopType":"NaptanPublicBusCoachTram","StopLetter":"R","Zone":null,"AccessibilitySummary":null,"HasDisruption":null,"Lines":[{"Id":"209","Name":"209","Uri":"/Line/209","FullName":null,"Type":"Line","Crowding":{"PassengerFlows":[],"TrainLoadings":[]},"RouteType":"Unknown","Status":"Unknown"},{"Id":"378","Name":"378","Uri":"/Line/378","FullName":null,"Type":"Line","Crowding":{"PassengerFlows":[],"TrainLoadings":[]},"RouteType":"Unknown","Status":"Unknown"}],"Status":true,"Id":"490006144N","Url":null,"Name":"Mortlake Bus Station","Lat":51.468,"Lon":-0.25929}],"ServiceType":"Regular"}],"OrderedLineRoutes":[{"Name":"Lonsdale Road &harr;  Mortlake Bus Station","NaptanIds":["490009353S","490013558S","490014260S","490010246WN","490003628BA","490007216BB","490003632BD","490003630BH","490001015BJ","490014596W","490006144S","490006144N"],"ServiceType":"Regular"}]}]}